xkcd_cli_viewer/__init__.py
xkcd_cli_viewer/__main__.py
xkcd_cli_viewer/cli/__init__.py
xkcd_cli_viewer/cli/comic.py
xkcd_cli_viewer/cli/links.py
xkcd_cli_viewer/cli/main.py
xkcd_cli_viewer/cli/scraper.py
xkcd_cli_viewer-0.1.2.dist-info/entry_points.txt
xkcd_cli_viewer-0.1.2.dist-info/LICENSE
xkcd_cli_viewer-0.1.2.dist-info/WHEEL
xkcd_cli_viewer-0.1.2.dist-info/METADATA
xkcd_cli_viewer-0.1.2.dist-info/RECORD
